<annotation>
	<folder>Dataset</folder>
	<filename>IMG_20220526_114810.jpg</filename>
	<path>D:\Downloads\Dataset\IMG_20220526_114810.jpg</path>
	<source>
		<database>Unknown</database>
	</source>
	<size>
		<width>3984</width>
		<height>1840</height>
		<depth>3</depth>
	</size>
	<segmented>0</segmented>
	<object>
		<name>a</name>
		<pose>Unspecified</pose>
		<truncated>0</truncated>
		<difficult>0</difficult>
		<bndbox>
			<xmin>2360</xmin>
			<ymin>741</ymin>
			<xmax>3035</xmax>
			<ymax>1577</ymax>
		</bndbox>
	</object>
	<object>
		<name>b</name>
		<pose>Unspecified</pose>
		<truncated>0</truncated>
		<difficult>0</difficult>
		<bndbox>
			<xmin>866</xmin>
			<ymin>859</ymin>
			<xmax>1723</xmax>
			<ymax>1656</ymax>
		</bndbox>
	</object>
	<object>
		<name>g</name>
		<pose>Unspecified</pose>
		<truncated>0</truncated>
		<difficult>0</difficult>
		<bndbox>
			<xmin>2602</xmin>
			<ymin>183</ymin>
			<xmax>3360</xmax>
			<ymax>947</ymax>
		</bndbox>
	</object>
	<object>
		<name>d</name>
		<pose>Unspecified</pose>
		<truncated>0</truncated>
		<difficult>0</difficult>
		<bndbox>
			<xmin>1687</xmin>
			<ymin>350</ymin>
			<xmax>2429</xmax>
			<ymax>1298</ymax>
		</bndbox>
	</object>
</annotation>
