<annotation>
	<folder>Dataset</folder>
	<filename>IMG_20220526_114632.jpg</filename>
	<path>D:\Downloads\Dataset\IMG_20220526_114632.jpg</path>
	<source>
		<database>Unknown</database>
	</source>
	<size>
		<width>1840</width>
		<height>3984</height>
		<depth>3</depth>
	</size>
	<segmented>0</segmented>
	<object>
		<name>d</name>
		<pose>Unspecified</pose>
		<truncated>0</truncated>
		<difficult>0</difficult>
		<bndbox>
			<xmin>291</xmin>
			<ymin>2269</ymin>
			<xmax>1461</xmax>
			<ymax>3387</ymax>
		</bndbox>
	</object>
	<object>
		<name>a</name>
		<pose>Unspecified</pose>
		<truncated>0</truncated>
		<difficult>0</difficult>
		<bndbox>
			<xmin>461</xmin>
			<ymin>1417</ymin>
			<xmax>1413</xmax>
			<ymax>2378</ymax>
		</bndbox>
	</object>
	<object>
		<name>v</name>
		<pose>Unspecified</pose>
		<truncated>0</truncated>
		<difficult>0</difficult>
		<bndbox>
			<xmin>105</xmin>
			<ymin>626</ymin>
			<xmax>1087</xmax>
			<ymax>1648</ymax>
		</bndbox>
	</object>
</annotation>
